pymatgen/analysis/alloys/__init__.py
pymatgen/analysis/alloys/anon_formulas.json
pymatgen/analysis/alloys/core.py
pymatgen/analysis/alloys/rgb.py
pymatgen_analysis_alloys-0.0.8.dist-info/METADATA
pymatgen_analysis_alloys-0.0.8.dist-info/WHEEL
pymatgen_analysis_alloys-0.0.8.dist-info/top_level.txt
pymatgen_analysis_alloys-0.0.8.dist-info/RECORD
