Metadata-Version: 2.4
Name: pymatgen-analysis-alloys
Version: 0.0.8
Summary: A pymatgen add-on library with classes useful for describing alloy (disordered) systems.
Home-page: https://github.com/materialsproject/pymatgen-analysis-alloys
Author: Rachel Woods-Robinson, Matthew Horton
Author-email: rwoodsrobinson@lbl.gov
Maintainer: Rachel Woods-Robinson, Matthew Horton
Keywords: pymatgen
Classifier: Programming Language :: Python :: 3
Classifier: Programming Language :: Python :: 3.7
Classifier: Programming Language :: Python :: 3.8
Classifier: Development Status :: 4 - Beta
Classifier: Intended Audience :: Science/Research
Classifier: License :: OSI Approved :: BSD License
Classifier: Operating System :: OS Independent
Classifier: Topic :: Scientific/Engineering :: Information Analysis
Classifier: Topic :: Scientific/Engineering :: Physics
Classifier: Topic :: Scientific/Engineering :: Chemistry
Classifier: Topic :: Software Development :: Libraries :: Python Modules
Requires-Dist: pymatgen>=2023.7.17
Requires-Dist: shapely>=1.8.2
Dynamic: author
Dynamic: author-email
Dynamic: classifier
Dynamic: description
Dynamic: description-content-type
Dynamic: home-page
Dynamic: keywords
Dynamic: maintainer
Dynamic: requires-dist
Dynamic: summary
